Workbook

Sheet P&L INPUT
B6: P&L STATEMENT
B8: ($ in thousands) | C8: 2023 | D8: =C8+1 -> 2024 | E8: =D8+1 -> 2025
B9: Revenues | C9: 33723297 | D9: 39000966 | E9: 45183036
B10: Cost of revenues | C10: 19715368 | D10: 21038464 | E10: 23275329
B11: Sales and marketing | C11: 2657883 | D11: 2917554 | E11: 3301306
B12: Technology and development | C12: 2675758 | D12: 2925295 | E12: 3391390
B13: General and administrative | C13: 1720285 | D13: 1702039 | E13: 1888408
B14: Operating income | C14: =C9-SUM(C10:C13) -> 6954003 | D14: =D9-SUM(D10:D13) -> 10417614 | E14: =E9-SUM(E10:E13) -> 13326603
B15: Other income (expense):
B16: Interest expense | C16: -699826 | D16: -718733 | E16: -776510
B17: Interest and other income (expense) | C17: -48772 | D17: 266776 | E17: 172459
B18: Income before income taxes | C18: =C14+C16+C17 -> 6205405 | D18: =D14+D16+D17 -> 9965657 | E18: =E14+E16+E17 -> 12722552
B19: Provision for income taxes | C19: -797415 | D19: -1254026 | E19: -1741351
B20: Net income | C20: =C18+C19 -> 5407990 | D20: =D18+D19 -> 8711631 | E20: =E18+E19 -> 10981201
B22: Key Margins
B23: Revenue Growth % | C23: 0 | D23: =D9/C9-1 -> 0.1564992 | E23: =E9/D9-1 -> 0.15851069
B24: Gross Margin % | C24: =(C9-C10)/C9 -> 0.4153784 | D24: =(D9-D10)/D9 -> 0.46056557 | E24: =(E9-E10)/E9 -> 0.48486576
B25: Operating Margin % | C25: =C14/C9 -> 0.20620768 | D25: =D14/D9 -> 0.26711169 | E25: =E14/E9 -> 0.29494705
B26: Net Margin % | C26: =C20/C9 -> 0.16036362 | D26: =D20/D9 -> 0.22336962 | E26: =E20/E9 -> 0.24303814
B27: Effective Tax Rate | C27: =-(C19/C18) -> 0.1285033 | D27: =-(D19/D18) -> 0.12583475 | E27: =-(E19/E18) -> 0.1368712

Sheet BALANCE SHEET INPUT
B6: BALANCE SHEET
B8: ($ in thousands) | C8: 2023 | D8: =C8+1 -> 2024 | E8: =D8+1 -> 2025
B9: Assets
B10: Current assets:
B11: Cash and cash equivalents | C11: 7116913 | D11: 7804733 | E11: 9033681
B12: Short-term investments | C12: 20973 | D12: 1779006 | E12: 28678
B13: Other current assets | C13: 2780247 | D13: 3516640 | E13: 3957832
B14: Total current assets | C14: =SUM(C11:C13) -> 9918133 | D14: =SUM(D11:D13) -> 13100379 | E14: =SUM(E11:E13) -> 13020191
B15: Content assets, net | C15: 31658056 | D15: 32452462 | E15: 32778392
B16: Property and equipment, net | C16: 1491444 | D16: 1593756 | E16: 2004350
B17: Other non-current assets | C17: 5664359 | D17: 6483777 | E17: 7794060
B18: Total assets | C18: =SUM(C14:C17) -> 48731992 | D18: =SUM(D14:D17) -> 53630374 | E18: =SUM(E14:E17) -> 55596993
B20: Liabilities and Stockholders’ Equity
B21: Current liabilities:
B22: Current content liabilities | C22: 4466470 | D22: 4393681 | E22: 4084854
B23: Accounts payable | C23: 747412 | D23: 899909 | E23: 900612
B24: Accrued expenses and other liabilities | C24: 1803960 | D24: 2156544 | E24: 3220869
B25: Deferred revenue | C25: 1442969 | D25: 1520813 | E25: 1775730
B26: Short-term debt | C26: 399844 | D26: 1784453 | E26: 998865
B27: Total current liabilities | C27: =SUM(C22:C26) -> 8860655 | D27: =SUM(D22:D26) -> 10755400 | E27: =SUM(E22:E26) -> 10980930
B28: Non-current content liabilities | C28: 2578173 | D28: 1780806 | E28: 1579476
B29: Long-term debt | C29: 14143417 | D29: 13798351 | E29: 13463971
B30: Other non-current liabilities | C30: 2561434 | D30: 2552250 | E30: 2957128
B31: Total liabilities | C31: =SUM(C27:C30) -> 28143679 | D31: =SUM(D27:D30) -> 28886807 | E31: =SUM(E27:E30) -> 28981505
B32: Stockholders’ equity:
B33: Common stock | C33: 5145172 | D33: 6252126 | E33: 7286410
B34: Treasury stock | C34: -6922200 | D34: -13171638 | E34: -22372658
B35: Accumulated other comprehensive income | C35: -223945 | D35: 362162 | E35: -580382
B36: Retained earnings | C36: 22589286 | D36: 31300917 | E36: 42282118
B37: Total stockholders’ equity | C37: =SUM(C33:C36) -> 20588313 | D37: =SUM(D33:D36) -> 24743567 | E37: =SUM(E33:E36) -> 26615488
B38: Total liabilities and stockholders’ equity | C38: =C31+C37 -> 48731992 | D38: =D31+D37 -> 53630374 | E38: =E31+E37 -> 55596993
B40: Check | C40: =C38-C18 -> 0 | D40: =D38-D18 -> 0 | E40: =E38-E18 -> 0

Sheet REVENUE BUILD BY REGION
B6: REVENUE BUILD BY REGION
B8: ($ in thousands) | C8: 2023 | D8: =C8+1 -> 2024 | E8: =D8+1 -> 2025 | F8: =E8+1 -> 2026 | G8: =F8+1 -> 2027 | H8: =G8+1 -> 2028 | I8: =H8+1 -> 2029 | J8: =I8+1 -> 2030
B10: United States and Canada (UCAN)
B11: Streaming Revenues | C11: 14873783 | D11: 17359369 | E11: 19957152 | F11: =E11*(1+F12) -> 22863858 | G11: =F11*(1+G12) -> 25850959 | H11: =G11*(1+H12) -> 28840553 | I11: =H11*(1+I12) -> 31599075 | J11: =I11*(1+J12) -> 33989460
B12: Year-over-Year Growth % | C12: - | D12: =D11/C11-1 -> 0.16711189 | E12: =E11/D11-1 -> 0.14964732 | F12: =E12-0.4% -> 0.14564732 | G12: =F12-1.5% -> 0.13064732 | H12: =G12-1.5% -> 0.11564732 | I12: =H12-2% -> 0.095647317 | J12: =I12-2% -> 0.075647317
B14: Europe, Middle East and Africa (EMEA)
B15: Streaming Revenues | C15: 10556487 | D15: 12387035 | E15: 14514646 | F15: =E15*(1+F16) -> 16688376 | G15: =F15*(1+G16) -> 19020762 | H15: =G15*(1+H16) -> 21488917 | I15: =H15*(1+I16) -> 23955009 | J15: =I15*(1+J16) -> 26344788
B16: Year-over-Year Growth % | C16: - | D16: =D15/C15-1 -> 0.17340504 | E16: =E15/D15-1 -> 0.17176112 | F16: =E16-2.2% -> 0.14976112 | G16: =F16-1% -> 0.13976112 | H16: =G16-1% -> 0.12976112 | I16: =H16-1.5% -> 0.11476112 | J16: =I16-1.5% -> 0.09976112
B18: Latin America (LATAM)
B19: Streaming Revenues | C19: 4446461 | D19: 4839816 | E19: 5357521 | F19: =E19*(1+F20) -> 5973464 | G19: =F19*(1+G20) -> 6630353.3 | H19: =G19*(1+H20) -> 7326327.7 | I19: =H19*(1+I20) -> 8058725.3 | J19: =I19*(1+J20) -> 8824045.6
B20: Year-over-Year Growth % | C20: - | D20: =D19/C19-1 -> 0.088464736 | E20: =E19/D19-1 -> 0.10696791 | F20: =E20+0.8% -> 0.11496791 | G20: =F20-0.5% -> 0.10996791 | H20: =G20-0.5% -> 0.10496791 | I20: =H20-0.5% -> 0.09996791 | J20: =I20-0.5% -> 0.09496791
B22: Asia-Pacific (APAC)
B23: Streaming Revenues | C23: 3763727 | D23: 4414746 | E23: 5353717 | F23: =E23*(1+F24) -> 6386078.5 | G23: =F23*(1+G24) -> 7489789.6 | H23: =G23*(1+H24) -> 8634460.1 | I23: =H23*(1+I24) -> 9781382.3 | J23: =I23*(1+J24) -> 10885023
B24: Year-over-Year Growth % | C24: - | D24: =D23/C23-1 -> 0.1729719 | E24: =E23/D23-1 -> 0.2126897 | F24: =AVERAGE(D24:E24) -> 0.1928308 | G24: =F24-2% -> 0.1728308 | H24: =G24-2% -> 0.1528308 | I24: =H24-2% -> 0.1328308 | J24: =I24-2% -> 0.1128308
B26: Total Streaming Revenues
B27: Total Revenues | C27: =C11+C15+C19+C23 -> 33640458 | D27: =D11+D15+D19+D23 -> 39000966 | E27: =E11+E15+E19+E23 -> 45183036 | F27: =F11+F15+F19+F23 -> 51911776 | G27: =G11+G15+G19+G23 -> 58991864 | H27: =H11+H15+H19+H23 -> 66290258 | I27: =I11+I15+I19+I23 -> 73394192 | J27: =J11+J15+J19+J23 -> 80043317
B28: Revenue Growth % | C28: - | D28: =D27/C27-1 -> 0.15934706 | E28: =E27/D27-1 -> 0.15851069 | F28: =F27/E27-1 -> 0.14892182 | G28: =G27/F27-1 -> 0.13638694 | H28: =H27/G27-1 -> 0.12371866 | I28: =I27/H27-1 -> 0.10716407 | J28: =J27/I27-1 -> 0.090594706
B30: Revenue Mix By Region (%)
B31: UCAN | C31: =C$11/C$27 -> 0.44213973 | D31: =D$11/D$27 -> 0.445101 | E31: =E$11/E$27 -> 0.44169568 | F31: =F$11/F$27 -> 0.44043682 | G31: =G$11/G$27 -> 0.43821228 | H31: =H$11/H$27 -> 0.43506473 | I31: =I$11/I$27 -> 0.43053918 | J31: =J$11/J$27 -> 0.42463833
B32: EMEA | C32: =C$15/C$27 -> 0.31380331 | D32: =D$15/D$27 -> 0.31760842 | E32: =E$15/E$27 -> 0.32124105 | F32: =F$15/F$27 -> 0.32147572 | G32: =G$15/G$27 -> 0.32243025 | H32: =H$15/H$27 -> 0.32416403 | I32: =I$15/I$27 -> 0.32638835 | J32: =J$15/J$27 -> 0.32913163
B33: LATAM | C33: =C$19/C$27 -> 0.13217599 | D33: =D$19/D$27 -> 0.12409477 | E33: =E$19/E$27 -> 0.11857373 | F33: =F$19/F$27 -> 0.11506954 | G33: =G$19/G$27 -> 0.11239437 | H33: =H$19/H$27 -> 0.11051892 | I33: =I$19/I$27 -> 0.10980059 | J33: =J$19/J$27 -> 0.11024088
B34: APAC | C34: =C$23/C$27 -> 0.11188097 | D34: =D$23/D$27 -> 0.11319581 | E34: =E$23/E$27 -> 0.11848954 | F34: =F$23/F$27 -> 0.12301792 | G34: =G$23/G$27 -> 0.12696309 | H34: =H$23/H$27 -> 0.13025232 | I34: =I$23/I$27 -> 0.13327189 | J34: =J$23/J$27 -> 0.13598916

Sheet OPERATING ASSUMPTIONS & WORKING
B6: OPERATING ASSUMPTIONS & WORKING CAPITAL
B8: ($ in thousands) | C8: 2023 | D8: =C8+1 -> 2024 | E8: =D8+1 -> 2025 | F8: =E8+1 -> 2026 | G8: =F8+1 -> 2027 | H8: =G8+1 -> 2028 | I8: =H8+1 -> 2029 | J8: =I8+1 -> 2030
B10: Cost of Revenues
B11: Cost of Revenues | C11: ='P&L INPUT'!C10 -> 19715368 | D11: ='P&L INPUT'!D10 -> 21038464 | E11: ='P&L INPUT'!E10 -> 23275329 | F11: ='REVENUE BUILD BY REGION'!F27*'OPERATING ASSUMPTIONS & WORKING'!F12 -> 26222416 | G11: ='REVENUE BUILD BY REGION'!G27*'OPERATING ASSUMPTIONS & WORKING'!G12 -> 28913933 | H11: ='REVENUE BUILD BY REGION'!H27*'OPERATING ASSUMPTIONS & WORKING'!H12 -> 31496772 | I11: ='REVENUE BUILD BY REGION'!I27*'OPERATING ASSUMPTIONS & WORKING'!I12 -> 33771181 | J11: ='REVENUE BUILD BY REGION'!J27*'OPERATING ASSUMPTIONS & WORKING'!J12 -> 35630021
B12: % of Revenues | C12: =C11/'REVENUE BUILD BY REGION'!C27 -> 0.58606122 | D12: =D11/'REVENUE BUILD BY REGION'!D27 -> 0.53943443 | E12: =E11/'REVENUE BUILD BY REGION'!E27 -> 0.51513424 | F12: =E12-1% -> 0.50513424 | G12: =F12-1.5% -> 0.49013424 | H12: =G12-1.5% -> 0.47513424 | I12: =H12-1.5% -> 0.46013424 | J12: =I12-1.5% -> 0.44513424
B14: Sales & Marketing
B15: Sales & Marketing | C15: ='P&L INPUT'!C11 -> 2657883 | D15: ='P&L INPUT'!D11 -> 2917554 | E15: ='P&L INPUT'!E11 -> 3301306 | F15: ='REVENUE BUILD BY REGION'!F27*'OPERATING ASSUMPTIONS & WORKING'!F16 -> 3735839.5 | G15: ='REVENUE BUILD BY REGION'!G27*'OPERATING ASSUMPTIONS & WORKING'!G16 -> 4068383.7 | H15: ='REVENUE BUILD BY REGION'!H27*'OPERATING ASSUMPTIONS & WORKING'!H16 -> 4372847.8 | I15: ='REVENUE BUILD BY REGION'!I27*'OPERATING ASSUMPTIONS & WORKING'!I16 -> 4621277.4 | J15: ='REVENUE BUILD BY REGION'!J27*'OPERATING ASSUMPTIONS & WORKING'!J16 -> 4799810.8
B16: % of Revenues | C16: =C15/'REVENUE BUILD BY REGION'!C27 -> 0.079008526 | D16: =D15/'REVENUE BUILD BY REGION'!D27 -> 0.074807224 | E16: =E15/'REVENUE BUILD BY REGION'!E27 -> 0.073065165 | F16: =E16-0.11% -> 0.071965165 | G16: =F16-0.3% -> 0.068965165 | H16: =G16-0.3% -> 0.065965165 | I16: =H16-0.3% -> 0.062965165 | J16: =I16-0.3% -> 0.059965165
B18: Technology & Development
B19: T&D Expense | C19: ='P&L INPUT'!C12 -> 2675758 | D19: ='P&L INPUT'!D12 -> 2925295 | E19: ='P&L INPUT'!E12 -> 3391390 | F19: ='REVENUE BUILD BY REGION'!F27*'OPERATING ASSUMPTIONS & WORKING'!F20 -> 3865294.9 | G19: ='REVENUE BUILD BY REGION'!G27*'OPERATING ASSUMPTIONS & WORKING'!G20 -> 4357075.5 | H19: ='REVENUE BUILD BY REGION'!H27*'OPERATING ASSUMPTIONS & WORKING'!H20 -> 4856352.9 | I19: ='REVENUE BUILD BY REGION'!I27*'OPERATING ASSUMPTIONS & WORKING'!I20 -> 5332742.9 | J19: ='REVENUE BUILD BY REGION'!J27*'OPERATING ASSUMPTIONS & WORKING'!J20 -> 5767835.2
B20: % of Revenues | C20: =C19/'REVENUE BUILD BY REGION'!C27 -> 0.07953988 | D20: =D19/'REVENUE BUILD BY REGION'!D27 -> 0.075005706 | E20: =E19/'REVENUE BUILD BY REGION'!E27 -> 0.075058923 | F20: =E20-0.06% -> 0.074458923 | G20: =F20-0.06% -> 0.073858923 | H20: =G20-0.06% -> 0.073258923 | I20: =H20-0.06% -> 0.072658923 | J20: =I20-0.06% -> 0.072058923
B22: General & Administrative
B23: G&A Expense | C23: ='P&L INPUT'!C13 -> 1720285 | D23: ='P&L INPUT'!D13 -> 1702039 | E23: ='P&L INPUT'!E13 -> 1888408 | F23: ='REVENUE BUILD BY REGION'!F27*'OPERATING ASSUMPTIONS & WORKING'!F24 -> 2076192 | G23: ='REVENUE BUILD BY REGION'!G27*'OPERATING ASSUMPTIONS & WORKING'!G24 -> 2300365.6 | H23: ='REVENUE BUILD BY REGION'!H27*'OPERATING ASSUMPTIONS & WORKING'!H24 -> 2518673.4 | I23: ='REVENUE BUILD BY REGION'!I27*'OPERATING ASSUMPTIONS & WORKING'!I24 -> 2715190.5 | J23: ='REVENUE BUILD BY REGION'!J27*'OPERATING ASSUMPTIONS & WORKING'!J24 -> 2881129.1
B24: % of Revenues | C24: =C23/'REVENUE BUILD BY REGION'!C27 -> 0.051137383 | D24: =D23/'REVENUE BUILD BY REGION'!D27 -> 0.043640945 | E24: =E23/'REVENUE BUILD BY REGION'!E27 -> 0.041794624 | F24: =E24-0.18% -> 0.039994624 | G24: =F24-0.1% -> 0.038994624 | H24: =G24-0.1% -> 0.037994624 | I24: =H24-0.1% -> 0.036994624 | J24: =I24-0.1% -> 0.035994624
B26: Working Capital - Current Assets
B27: Other Current Assets | C27: ='BALANCE SHEET INPUT'!C13 -> 2780247 | D27: ='BALANCE SHEET INPUT'!D13 -> 3516640 | E27: ='BALANCE SHEET INPUT'!E13 -> 3957832 | F27: ='REVENUE BUILD BY REGION'!F27*'OPERATING ASSUMPTIONS & WORKING'!F28 -> 4506106.3 | G27: ='REVENUE BUILD BY REGION'!G27*'OPERATING ASSUMPTIONS & WORKING'!G28 -> 5202427.9 | H27: ='REVENUE BUILD BY REGION'!H27*'OPERATING ASSUMPTIONS & WORKING'!H28 -> 5802333.2 | I27: ='REVENUE BUILD BY REGION'!I27*'OPERATING ASSUMPTIONS & WORKING'!I28 -> 6422512 | J27: ='REVENUE BUILD BY REGION'!J27*'OPERATING ASSUMPTIONS & WORKING'!J28 -> 7023139.2
B28: % of Revenues | C28: =C27/'REVENUE BUILD BY REGION'!C27 -> 0.082645932 | D28: =D27/'REVENUE BUILD BY REGION'!D27 -> 0.090168023 | E28: =E27/'REVENUE BUILD BY REGION'!E27 -> 0.08759553 | F28: =AVERAGE(C28:E28) -> 0.086803162 | G28: =AVERAGE(D28:F28) -> 0.088188905 | H28: =AVERAGE(E28:G28) -> 0.087529199 | I28: =AVERAGE(F28:H28) -> 0.087507089 | J28: =AVERAGE(G28:I28) -> 0.087741731
B30: Working Capital - Current Liabilities
B31: Accounts Payable | C31: ='BALANCE SHEET INPUT'!C23 -> 747412 | D31: ='BALANCE SHEET INPUT'!D23 -> 899909 | E31: ='BALANCE SHEET INPUT'!E23 -> 900612 | F31: =(F32*F11)/365 -> 1043463.6 | G31: =(G32*G11)/365 -> 1168711.9 | H31: =(H32*H11)/365 -> 1248395.9 | I31: =(I32*I11)/365 -> 1349145.8 | J31: =(J32*J11)/365 -> 1425268.2
B32: Days Payable Outstanding | C32: =(C31/C11)*365 -> 13.837194 | D32: =(D31/D11)*365 -> 15.612679 | E32: =(E31/E11)*365 -> 14.123254 | F32: =AVERAGE(C32:E32) -> 14.524376 | G32: =AVERAGE(D32:F32) -> 14.753436 | H32: =AVERAGE(E32:G32) -> 14.467022 | I32: =AVERAGE(F32:H32) -> 14.581611 | J32: =AVERAGE(G32:I32) -> 14.60069
B33: Accrued Expenses & Other Liabilities | C33: ='BALANCE SHEET INPUT'!C24 -> 1803960 | D33: ='BALANCE SHEET INPUT'!D24 -> 2156544 | E33: ='BALANCE SHEET INPUT'!E24 -> 3220869 | F33: ='REVENUE BUILD BY REGION'!F27*'OPERATING ASSUMPTIONS & WORKING'!F34 -> 3700526.7 | G33: ='REVENUE BUILD BY REGION'!G27*'OPERATING ASSUMPTIONS & WORKING'!G34 -> 4205230.2 | H33: ='REVENUE BUILD BY REGION'!H27*'OPERATING ASSUMPTIONS & WORKING'!H34 -> 4725495.6 | I33: ='REVENUE BUILD BY REGION'!I27*'OPERATING ASSUMPTIONS & WORKING'!I34 -> 5231898.9 | J33: ='REVENUE BUILD BY REGION'!J27*'OPERATING ASSUMPTIONS & WORKING'!J34 -> 5705881.3
B34: % of Revenues | C34: =C33/'REVENUE BUILD BY REGION'!C27 -> 0.053624716 | D34: =D33/'REVENUE BUILD BY REGION'!D27 -> 0.05529463 | E34: =E33/'REVENUE BUILD BY REGION'!E27 -> 0.071284918 | F34: =E34 -> 0.071284918 | G34: =F34 -> 0.071284918 | H34: =G34 -> 0.071284918 | I34: =H34 -> 0.071284918 | J34: =I34 -> 0.071284918
B35: Deferred Revenue | C35: ='BALANCE SHEET INPUT'!C25 -> 1442969 | D35: ='BALANCE SHEET INPUT'!D25 -> 1520813 | E35: ='BALANCE SHEET INPUT'!E25 -> 1775730 | F35: ='REVENUE BUILD BY REGION'!F27*'OPERATING ASSUMPTIONS & WORKING'!F36 -> 2032217.6 | G35: ='REVENUE BUILD BY REGION'!G27*'OPERATING ASSUMPTIONS & WORKING'!G36 -> 2313906.8 | H35: ='REVENUE BUILD BY REGION'!H27*'OPERATING ASSUMPTIONS & WORKING'!H36 -> 2597639.9 | I35: ='REVENUE BUILD BY REGION'!I27*'OPERATING ASSUMPTIONS & WORKING'!I36 -> 2877419.9 | J35: ='REVENUE BUILD BY REGION'!J27*'OPERATING ASSUMPTIONS & WORKING'!J36 -> 3137332
B36: % of Revenues | C36: =C35/'REVENUE BUILD BY REGION'!C27 -> 0.042893857 | D36: =D35/'REVENUE BUILD BY REGION'!D27 -> 0.038994239 | E36: =E35/'REVENUE BUILD BY REGION'!E27 -> 0.039300812 | F36: =AVERAGE(D36:E36) -> 0.039147526 | G36: =AVERAGE(E36:F36) -> 0.039224169 | H36: =AVERAGE(F36:G36) -> 0.039185847 | I36: =AVERAGE(G36:H36) -> 0.039205008 | J36: =AVERAGE(H36:I36) -> 0.039195428
B38: Stock-based Compensation Expense
B39: SBC Expense | C39: 339368 | D39: 272588 | E39: 368449 | F39: ='FORECASTED P&L '!F11*'OPERATING ASSUMPTIONS & WORKING'!F40 -> 436182.81 | G39: ='FORECASTED P&L '!G11*'OPERATING ASSUMPTIONS & WORKING'!G40 -> 495672.45 | H39: ='FORECASTED P&L '!H11*'OPERATING ASSUMPTIONS & WORKING'!H40 -> 556996.38 | I39: ='FORECASTED P&L '!I11*'OPERATING ASSUMPTIONS & WORKING'!I40 -> 616686.38 | J39: ='FORECASTED P&L '!J11*'OPERATING ASSUMPTIONS & WORKING'!J40 -> 672554.9
B40: % of Revenues | C40: =C39/'FORECASTED P&L '!C11 -> 0.01006331 | D40: =D39/'FORECASTED P&L '!D11 -> 0.0069892628 | E40: =E39/'FORECASTED P&L '!E11 -> 0.008154587 | F40: =AVERAGE($C$40:$E$40) -> 0.0084023867 | G40: =AVERAGE($C$40:$E$40) -> 0.0084023867 | H40: =AVERAGE($C$40:$E$40) -> 0.0084023867 | I40: =AVERAGE($C$40:$E$40) -> 0.0084023867 | J40: =AVERAGE($C$40:$E$40) -> 0.0084023867

Sheet SCHEDULES
B6: SCHEDULES
B8: ($ in thousands) | C8: 2023 | D8: =C8+1 -> 2024 | E8: =D8+1 -> 2025 | F8: =E8+1 -> 2026 | G8: =F8+1 -> 2027 | H8: =G8+1 -> 2028 | I8: =H8+1 -> 2029 | J8: =I8+1 -> 2030
B10: PP&E Schedules
B11: Opening PP&E | C11: 1398257 | D11: =C16 -> 1491444 | E11: =D16 -> 1593756 | F11: =E16 -> 2004350 | G11: =F16 -> 2675696.1 | H11: =G16 -> 3553085.4 | I11: =H16 -> 4662796.6 | J11: =I16 -> 6022604.6
B12: Add: Capital Expenditures | C12: 348552 | D12: 439538 | E12: 688220 | F12: =F13*'REVENUE BUILD BY REGION'!F27 -> 920490.41 | G12: =G13*'REVENUE BUILD BY REGION'!G27 -> 1193512.9 | H12: =H13*'REVENUE BUILD BY REGION'!H27 -> 1506898.4 | I12: =I13*'REVENUE BUILD BY REGION'!I27 -> 1851869.2 | J12: =J13*'REVENUE BUILD BY REGION'!J27 -> 2219747.1
B13: Capex % of Revenues | C13: =C12/'REVENUE BUILD BY REGION'!C27 -> 0.010361096 | D13: =D12/'REVENUE BUILD BY REGION'!D27 -> 0.011269926 | E13: =E12/'REVENUE BUILD BY REGION'!E27 -> 0.015231823 | F13: =E13+0.25% -> 0.017731823 | G13: =F13+0.25% -> 0.020231823 | H13: =G13+0.25% -> 0.022731823 | I13: =H13+0.25% -> 0.025231823 | J13: =I13+0.25% -> 0.027731823
B14: Less: Depreciation | C14: 356947 | D14: 328914 | E14: 333389 | F14: =AVERAGE(F11:F12)/F18 -> 249144.31 | G14: =AVERAGE(G11:G12)/G18 -> 316123.65 | H14: =AVERAGE(H11:H12)/H18 -> 397187.23 | I14: =AVERAGE(I11:I12)/I18 -> 492061.23 | J14: =AVERAGE(J11:J12)/J18 -> 599899.98
B15: Add/Less: Other/FX Adjustments | C15: =C16-(C11+C12-C14) -> 101582 | D15: =D16-(D11+D12-D14) -> -8312 | E15: =E16-(E11+E12-E14) -> 55763 | F15: 0 | G15: 0 | H15: 0 | I15: 0 | J15: 0
B16: Closing PP&E | C16: ='BALANCE SHEET INPUT'!C16 -> 1491444 | D16: ='BALANCE SHEET INPUT'!D16 -> 1593756 | E16: ='BALANCE SHEET INPUT'!E16 -> 2004350 | F16: =F11+F12-F14+F15 -> 2675696.1 | G16: =G11+G12-G14+G15 -> 3553085.4 | H16: =H11+H12-H14+H15 -> 4662796.6 | I16: =I11+I12-I14+I15 -> 6022604.6 | J16: =J11+J12-J14+J15 -> 7642451.7
B18: Useful Life (Yrs) | C18: =(C11+C12)/C14 -> 4.8937489 | D18: =(D11+D12)/D14 -> 5.8707808 | E18: =(E11+E12)/E14 -> 6.8447849 | F18: =AVERAGE(C18:E18) -> 5.8697716 | G18: =F18+0.25 -> 6.1197716 | H18: =G18+0.25 -> 6.3697716 | I18: =H18+0.25 -> 6.6197716 | J18: =I18+0.25 -> 6.8697716
B20: Content Assets Schedules
B21: Opening Content Assets | C21: 32736713 | D21: =C25 -> 31658056 | E21: =D25 -> 32452462 | F21: =E25 -> 32778392 | G21: =F25 -> 34167946 | H21: =G25 -> 36536813 | I21: =H25 -> 39570924 | J21: =I25 -> 42964312
B22: Add: Content Additions | C22: 12554703 | D22: 16223617 | E22: 17096617 | F22: =F23*'REVENUE BUILD BY REGION'!F27 -> 17566205 | G22: =G23*'REVENUE BUILD BY REGION'!G27 -> 19667047 | H22: =H23*'REVENUE BUILD BY REGION'!H27 -> 21768776 | I22: =I23*'REVENUE BUILD BY REGION'!I27 -> 23734636 | J22: =J23*'REVENUE BUILD BY REGION'!J27 -> 25484652
B23: Content Additions % of Revenues | C23: =C22/'REVENUE BUILD BY REGION'!C27 -> 0.3732025 | D23: =D22/'REVENUE BUILD BY REGION'!D27 -> 0.41597988 | E23: =E22/'REVENUE BUILD BY REGION'!E27 -> 0.37838575 | F23: =E23-4% -> 0.33838575 | G23: =F23-0.5% -> 0.33338575 | H23: =G23-0.5% -> 0.32838575 | I23: =H23-0.5% -> 0.32338575 | J23: =I23-0.5% -> 0.31838575
B24: Less: Content Amortization | C24: 14197437 | D24: 15301517 | E24: 16422166 | F24: =(F21+F22)/F27 -> 16176651 | G24: =(G21+G22)/G27 -> 17298180 | H24: =(H21+H22)/H27 -> 18734665 | I24: =(I21+I22)/I27 -> 20341248 | J24: =(J21+J22)/J27 -> 21993919
B25: Closing Content Assets | C25: ='BALANCE SHEET INPUT'!C15 -> 31658056 | D25: ='BALANCE SHEET INPUT'!D15 -> 32452462 | E25: ='BALANCE SHEET INPUT'!E15 -> 32778392 | F25: =F21+F22-F24 -> 34167946 | G25: =G21+G22-G24 -> 36536813 | H25: =H21+H22-H24 -> 39570924 | I25: =I21+I22-I24 -> 42964312 | J25: =J21+J22-J24 -> 46455044
B27: Useful Life (Yrs) | C27: =(C21+C22)/C24 -> 3.1901121 | D27: =(D21+D22)/D24 -> 3.1292108 | E27: =(E21+E22)/E24 -> 3.0172073 | F27: =AVERAGE($C$27:$E$27) -> 3.1121768 | G27: =AVERAGE($C$27:$E$27) -> 3.1121768 | H27: =AVERAGE($C$27:$E$27) -> 3.1121768 | I27: =AVERAGE($C$27:$E$27) -> 3.1121768 | J27: =AVERAGE($C$27:$E$27) -> 3.1121768
B29: Debt Schedules
B30: Opening Total Debt | C30: 14353076 | D30: =C34 -> 14543261 | E30: =D34 -> 15582804 | F30: =E34 -> 14462836 | G30: =F34 -> 13462836 | H30: =G34 -> 11936836 | I30: =H34 -> 8436836 | J30: =I34 -> 4035836
B31: Add: New Borrowings | C31: 0 | D31: 1794460 | E31: 0 | F31: 0 | G31: 0 | H31: 0 | I31: 0 | J31: 0
B32: Less: Repayments | C32: 0 | D32: -400000 | E32: -1833450 | F32: -1000000 | G32: -1526000 | H32: -3500000 | I32: -4401000 | J32: -2292000
B33: Non-Cash Adjustments | C33: =C34-C30 -> 190185 | D33: =D34-SUM(D30:D32) -> -354917 | E33: =E34-SUM(E30:E32) -> 713482 | F33: 0 | G33: 0 | H33: 0 | I33: 0 | J33: 0
B34: Total Debt | C34: ='BALANCE SHEET INPUT'!C29+'BALANCE SHEET INPUT'!C26 -> 14543261 | D34: ='BALANCE SHEET INPUT'!D29+'BALANCE SHEET INPUT'!D26 -> 15582804 | E34: ='BALANCE SHEET INPUT'!E29+'BALANCE SHEET INPUT'!E26 -> 14462836 | F34: =SUM(F30:F33) -> 13462836 | G34: =SUM(G30:G33) -> 11936836 | H34: =SUM(H30:H33) -> 8436836 | I34: =SUM(I30:I33) -> 4035836 | J34: =SUM(J30:J33) -> 1743836 | K34: =F34+G32 -> 11936836
B36: Interest Expense | C36: ='P&L INPUT'!C16 -> -699826 | D36: ='P&L INPUT'!D16 -> -718733 | E36: ='P&L INPUT'!E16 -> -776510 | F36: =-(F34*F37) -> -615117.29 | G36: =-(G34*G37) -> -533457.48 | H36: =-(H34*H37) -> -368605.56 | I36: =-(I34*I37) -> -172289.93 | J36: =-(J34*J37) -> -72700.563
B37: Effective Interest Rate | C37: =-(C36/C34) -> 0.048120294 | D37: =-(D36/D34) -> 0.04612347 | E37: =-(E36/E34) -> 0.053690023 | F37: =E37-0.8% -> 0.045690023 | G37: =F37-0.1% -> 0.044690023 | H37: =G37-0.1% -> 0.043690023 | I37: =H37-0.1% -> 0.042690023 | J37: =I37-0.1% -> 0.041690023

Sheet FORECASTED P&L 
B6: FORECASTED P&L STATEMENT
B8: ($ in thousands) | C8: 2023 | D8: =C8+1 -> 2024 | E8: =D8+1 -> 2025 | F8: =E8+1 -> 2026 | G8: =F8+1 -> 2027 | H8: =G8+1 -> 2028 | I8: =H8+1 -> 2029 | J8: =I8+1 -> 2030
B9: Streaming Revenues | C9: ='REVENUE BUILD BY REGION'!C27 -> 33640458 | D9: ='REVENUE BUILD BY REGION'!D27 -> 39000966 | E9: ='REVENUE BUILD BY REGION'!E27 -> 45183036 | F9: ='REVENUE BUILD BY REGION'!F27 -> 51911776 | G9: ='REVENUE BUILD BY REGION'!G27 -> 58991864 | H9: ='REVENUE BUILD BY REGION'!H27 -> 66290258 | I9: ='REVENUE BUILD BY REGION'!I27 -> 73394192 | J9: ='REVENUE BUILD BY REGION'!J27 -> 80043317
B10: DVD Revenues | C10: 82839 | D10: 0 | E10: 0 | F10: 0 | G10: 0 | H10: 0 | I10: 0 | J10: 0
B11: Total Revenues | C11: =C9+C10 -> 33723297 | D11: =D9+D10 -> 39000966 | E11: =E9+E10 -> 45183036 | F11: =F9+F10 -> 51911776 | G11: =G9+G10 -> 58991864 | H11: =H9+H10 -> 66290258 | I11: =I9+I10 -> 73394192 | J11: =J9+J10 -> 80043317
B12: Cost of Revenues | C12: ='OPERATING ASSUMPTIONS & WORKING'!C11 -> 19715368 | D12: ='OPERATING ASSUMPTIONS & WORKING'!D11 -> 21038464 | E12: ='OPERATING ASSUMPTIONS & WORKING'!E11 -> 23275329 | F12: ='OPERATING ASSUMPTIONS & WORKING'!F11 -> 26222416 | G12: ='OPERATING ASSUMPTIONS & WORKING'!G11 -> 28913933 | H12: ='OPERATING ASSUMPTIONS & WORKING'!H11 -> 31496772 | I12: ='OPERATING ASSUMPTIONS & WORKING'!I11 -> 33771181 | J12: ='OPERATING ASSUMPTIONS & WORKING'!J11 -> 35630021
B13: Gross Margin | C13: =C11-C12 -> 14007929 | D13: =D11-D12 -> 17962502 | E13: =E11-E12 -> 21907707 | F13: =F11-F12 -> 25689360 | G13: =G11-G12 -> 30077931 | H13: =H11-H12 -> 34793487 | I13: =I11-I12 -> 39623011 | J13: =J11-J12 -> 44413296
B14: Operating Expenses
B15: Sales & Marketing | C15: ='OPERATING ASSUMPTIONS & WORKING'!C15 -> 2657883 | D15: ='OPERATING ASSUMPTIONS & WORKING'!D15 -> 2917554 | E15: ='OPERATING ASSUMPTIONS & WORKING'!E15 -> 3301306 | F15: ='OPERATING ASSUMPTIONS & WORKING'!F15 -> 3735839.5 | G15: ='OPERATING ASSUMPTIONS & WORKING'!G15 -> 4068383.7 | H15: ='OPERATING ASSUMPTIONS & WORKING'!H15 -> 4372847.8 | I15: ='OPERATING ASSUMPTIONS & WORKING'!I15 -> 4621277.4 | J15: ='OPERATING ASSUMPTIONS & WORKING'!J15 -> 4799810.8
B16: Technology & Development | C16: ='OPERATING ASSUMPTIONS & WORKING'!C19 -> 2675758 | D16: ='OPERATING ASSUMPTIONS & WORKING'!D19 -> 2925295 | E16: ='OPERATING ASSUMPTIONS & WORKING'!E19 -> 3391390 | F16: ='OPERATING ASSUMPTIONS & WORKING'!F19 -> 3865294.9 | G16: ='OPERATING ASSUMPTIONS & WORKING'!G19 -> 4357075.5 | H16: ='OPERATING ASSUMPTIONS & WORKING'!H19 -> 4856352.9 | I16: ='OPERATING ASSUMPTIONS & WORKING'!I19 -> 5332742.9 | J16: ='OPERATING ASSUMPTIONS & WORKING'!J19 -> 5767835.2
B17: General & Administrative | C17: ='OPERATING ASSUMPTIONS & WORKING'!C23 -> 1720285 | D17: ='OPERATING ASSUMPTIONS & WORKING'!D23 -> 1702039 | E17: ='OPERATING ASSUMPTIONS & WORKING'!E23 -> 1888408 | F17: ='OPERATING ASSUMPTIONS & WORKING'!F23 -> 2076192 | G17: ='OPERATING ASSUMPTIONS & WORKING'!G23 -> 2300365.6 | H17: ='OPERATING ASSUMPTIONS & WORKING'!H23 -> 2518673.4 | I17: ='OPERATING ASSUMPTIONS & WORKING'!I23 -> 2715190.5 | J17: ='OPERATING ASSUMPTIONS & WORKING'!J23 -> 2881129.1
B18: EBITDA | C18: =C13-SUM(C15:C17) -> 6954003 | D18: =D13-SUM(D15:D17) -> 10417614 | E18: =E13-SUM(E15:E17) -> 13326603 | F18: =F13-SUM(F15:F17) -> 16012034 | G18: =G13-SUM(G15:G17) -> 19352107 | H18: =H13-SUM(H15:H17) -> 23045612 | I18: =I13-SUM(I15:I17) -> 26953800 | J18: =J13-SUM(J15:J17) -> 30964521
B19: Less: Depreciation | C19: =SCHEDULES!C14 -> 356947 | D19: =SCHEDULES!D14 -> 328914 | E19: =SCHEDULES!E14 -> 333389 | F19: =SCHEDULES!F14 -> 249144.31 | G19: =SCHEDULES!G14 -> 316123.65 | H19: =SCHEDULES!H14 -> 397187.23 | I19: =SCHEDULES!I14 -> 492061.23 | J19: =SCHEDULES!J14 -> 599899.98
B20: EBIT (Operating Income) | C20: =C18-C19 -> 6597056 | D20: =D18-D19 -> 10088700 | E20: =E18-E19 -> 12993214 | F20: =F18-F19 -> 15762890 | G20: =G18-G19 -> 19035983 | H20: =H18-H19 -> 22648425 | I20: =I18-I19 -> 26461739 | J20: =J18-J19 -> 30364621
B21: Interest Expense | C21: =SCHEDULES!C36 -> -699826 | D21: =SCHEDULES!D36 -> -718733 | E21: =SCHEDULES!E36 -> -776510 | F21: =SCHEDULES!F36 -> -615117.29 | G21: =SCHEDULES!G36 -> -533457.48 | H21: =SCHEDULES!H36 -> -368605.56 | I21: =SCHEDULES!I36 -> -172289.93 | J21: =SCHEDULES!J36 -> -72700.563
B22: Interest and Other Income (Expense) | C22: ='P&L INPUT'!C17 -> -48772 | D22: ='P&L INPUT'!D17 -> 266776 | E22: ='P&L INPUT'!E17 -> 172459 | F22: =F11*F23 -> 159384.68 | G22: =G11*G23 -> 181122.67 | H22: =H11*H23 -> 203530.92 | I22: =I11*I23 -> 225342.12 | J22: =J11*J23 -> 245756.93
B23: % of Revenues | C23: =C22/C11 -> -0.0014462406 | D23: =D22/D11 -> 0.0068402408 | E23: =E22/E11 -> 0.0038168971 | F23: =AVERAGE($C$23:$E$23) -> 0.0030702991 | G23: =AVERAGE($C$23:$E$23) -> 0.0030702991 | H23: =AVERAGE($C$23:$E$23) -> 0.0030702991 | I23: =AVERAGE($C$23:$E$23) -> 0.0030702991 | J23: =AVERAGE($C$23:$E$23) -> 0.0030702991
B24: EBT (Income Before Income Taxes) | C24: =C18+C21+C22 -> 6205405 | D24: =D18+D21+D22 -> 9965657 | E24: =E18+E21+E22 -> 12722552 | F24: =F18+F21+F22 -> 15556301 | G24: =G18+G21+G22 -> 18999772 | H24: =H18+H21+H22 -> 22880538 | I24: =I18+I21+I22 -> 27006852 | J24: =J18+J21+J22 -> 31137577
B25: Provision for Income Taxes | C25: ='P&L INPUT'!C19 -> -797415 | D25: ='P&L INPUT'!D19 -> -1254026 | E25: ='P&L INPUT'!E19 -> -1741351 | F25: =-(F24*F26) -> -2206991.2 | G25: =-(G24*G26) -> -2790519.4 | H25: =-(H24*H26) -> -3474894.8 | I25: =-(I24*I26) -> -4236597.4 | J25: =-(J24*J26) -> -5040277.1
B26: Effective Tax Rate % | C26: =-(C25/C24) -> 0.1285033 | D26: =-(D25/D24) -> 0.12583475 | E26: =-(E25/E24) -> 0.1368712 | F26: =E26+0.5% -> 0.1418712 | G26: =F26+0.5% -> 0.1468712 | H26: =G26+0.5% -> 0.1518712 | I26: =H26+0.5% -> 0.1568712 | J26: =I26+0.5% -> 0.1618712
B27: Net Income | C27: =SUM(C24:C25) -> 5407990 | D27: =SUM(D24:D25) -> 8711631 | E27: =SUM(E24:E25) -> 10981201 | F27: =F24+F25 -> 13349310 | G27: =G24+G25 -> 16209253 | H27: =H24+H25 -> 19405643 | I27: =I24+I25 -> 22770255 | J27: =J24+J25 -> 26097300

Sheet FORECASTED BALANCE SHEET
B6: FORECASTED BALANCE SHEET
B8: ($ in thousands) | C8: 2023 | D8: =C8+1 -> 2024 | E8: =D8+1 -> 2025 | F8: =E8+1 -> 2026 | G8: =F8+1 -> 2027 | H8: =G8+1 -> 2028 | I8: =H8+1 -> 2029 | J8: =I8+1 -> 2030
B9: Assets
B10: Current assets:
B11: Cash and cash equivalents | C11: 7116913 | D11: 7804733 | E11: 9033681 | F11: =E11+'FORECASTED CASH FLOW STATEMENT'!E28 -> 19244284 | G11: =F11+'FORECASTED CASH FLOW STATEMENT'!F28 -> 30399354 | H11: =G11+'FORECASTED CASH FLOW STATEMENT'!G28 -> 41844233 | I11: =H11+'FORECASTED CASH FLOW STATEMENT'!H28 -> 55009644 | J11: =I11+'FORECASTED CASH FLOW STATEMENT'!I28 -> 73068097
B12: Short-term investments | C12: 20973 | D12: 1779006 | E12: 28678 | F12: ='FORECASTED P&L '!F11*'FORECASTED BALANCE SHEET'!F13 -> 1200436.9 | G12: ='FORECASTED P&L '!G11*'FORECASTED BALANCE SHEET'!G13 -> 1659120.1 | H12: ='FORECASTED P&L '!H11*'FORECASTED BALANCE SHEET'!H13 -> 2195835.5 | I12: ='FORECASTED P&L '!I11*'FORECASTED BALANCE SHEET'!I13 -> 2798121.1 | J12: ='FORECASTED P&L '!J11*'FORECASTED BALANCE SHEET'!J13 -> 3451832.7
B13: % of Revenues | C13: =C12/'FORECASTED P&L '!C11 -> 0.00062191428 | D13: =D12/'FORECASTED P&L '!D11 -> 0.045614409 | E13: =E12/'FORECASTED P&L '!E11 -> 0.00063470724 | F13: =AVERAGE(D13:E13) -> 0.023124558 | G13: =F13+0.5% -> 0.028124558 | H13: =G13+0.5% -> 0.033124558 | I13: =H13+0.5% -> 0.038124558 | J13: =I13+0.5% -> 0.043124558
B14: Other current assets | C14: 2780247 | D14: 3516640 | E14: 3957832 | F14: ='OPERATING ASSUMPTIONS & WORKING'!F27 -> 4506106.3 | G14: ='OPERATING ASSUMPTIONS & WORKING'!G27 -> 5202427.9 | H14: ='OPERATING ASSUMPTIONS & WORKING'!H27 -> 5802333.2 | I14: ='OPERATING ASSUMPTIONS & WORKING'!I27 -> 6422512 | J14: ='OPERATING ASSUMPTIONS & WORKING'!J27 -> 7023139.2
B15: Total current assets | C15: =C11+C12+C14 -> 9918133 | D15: =D11+D12+D14 -> 13100379 | E15: =E11+E12+E14 -> 13020191 | F15: =F11+F12+F14 -> 24950827 | G15: =G11+G12+G14 -> 37260902 | H15: =H11+H12+H14 -> 49842402 | I15: =I11+I12+I14 -> 64230277 | J15: =J11+J12+J14 -> 83543069
B16: Content assets, net | C16: 31658056 | D16: 32452462 | E16: 32778392 | F16: =SCHEDULES!F25 -> 34167946 | G16: =SCHEDULES!G25 -> 36536813 | H16: =SCHEDULES!H25 -> 39570924 | I16: =SCHEDULES!I25 -> 42964312 | J16: =SCHEDULES!J25 -> 46455044
B17: Property and equipment, net | C17: 1491444 | D17: 1593756 | E17: 2004350 | F17: =SCHEDULES!F16 -> 2675696.1 | G17: =SCHEDULES!G16 -> 3553085.4 | H17: =SCHEDULES!H16 -> 4662796.6 | I17: =SCHEDULES!I16 -> 6022604.6 | J17: =SCHEDULES!J16 -> 7642451.7
B18: Other non-current assets | C18: 5664359 | D18: 6483777 | E18: 7794060 | F18: =F19*'FORECASTED P&L '!F11 -> 8768107 | G18: =G19*'FORECASTED P&L '!G11 -> 9963962.3 | H18: =H19*'FORECASTED P&L '!H11 -> 11196690 | I18: =I19*'FORECASTED P&L '!I11 -> 12396573 | J18: =J19*'FORECASTED P&L '!J11 -> 13519637
B19: % of Revenues | C19: =C18/'FORECASTED P&L '!C11 -> 0.16796575 | D19: =D18/'FORECASTED P&L '!D11 -> 0.16624657 | E19: =E18/'FORECASTED P&L '!E11 -> 0.1724997 | F19: =AVERAGE($C$19:$E$19) -> 0.16890401 | G19: =AVERAGE($C$19:$E$19) -> 0.16890401 | H19: =AVERAGE($C$19:$E$19) -> 0.16890401 | I19: =AVERAGE($C$19:$E$19) -> 0.16890401 | J19: =AVERAGE($C$19:$E$19) -> 0.16890401
B20: Total assets | C20: =C15+C16+C17+C18 -> 48731992 | D20: =D15+D16+D17+D18 -> 53630374 | E20: =E15+E16+E17+E18 -> 55596993 | F20: =F15+F16+F17+F18 -> 70562577 | G20: =G15+G16+G17+G18 -> 87314763 | H20: =H15+H16+H17+H18 -> 1.0527281e+08 | I20: =I15+I16+I17+I18 -> 1.2561377e+08 | J20: =J15+J16+J17+J18 -> 1.511602e+08
B22: Liabilities and Stockholders’ Equity
B23: Current liabilities:
B24: Current content liabilities | C24: 4466470 | D24: 4393681 | E24: 4084854 | F24: =F25*SCHEDULES!F22 -> 5067899.3 | G24: =G25*SCHEDULES!G22 -> 5673998 | H24: =H25*SCHEDULES!H22 -> 6280352.8 | I24: =I25*SCHEDULES!I22 -> 6847508.8 | J24: =J25*SCHEDULES!J22 -> 7352393.3
B25: % of Content Spend | C25: =C24/SCHEDULES!C22 -> 0.35576071 | D25: =D24/SCHEDULES!D22 -> 0.27082006 | E25: =E24/SCHEDULES!E22 -> 0.23892762 | F25: =AVERAGE($C$25:$E$25) -> 0.2885028 | G25: =AVERAGE($C$25:$E$25) -> 0.2885028 | H25: =AVERAGE($C$25:$E$25) -> 0.2885028 | I25: =AVERAGE($C$25:$E$25) -> 0.2885028 | J25: =AVERAGE($C$25:$E$25) -> 0.2885028
B26: Accounts payable | C26: 747412 | D26: 899909 | E26: 900612 | F26: ='OPERATING ASSUMPTIONS & WORKING'!F31 -> 1043463.6 | G26: ='OPERATING ASSUMPTIONS & WORKING'!G31 -> 1168711.9 | H26: ='OPERATING ASSUMPTIONS & WORKING'!H31 -> 1248395.9 | I26: ='OPERATING ASSUMPTIONS & WORKING'!I31 -> 1349145.8 | J26: ='OPERATING ASSUMPTIONS & WORKING'!J31 -> 1425268.2
B27: Accrued expenses and other liabilities | C27: 1803960 | D27: 2156544 | E27: 3220869 | F27: ='OPERATING ASSUMPTIONS & WORKING'!F33 -> 3700526.7 | G27: ='OPERATING ASSUMPTIONS & WORKING'!G33 -> 4205230.2 | H27: ='OPERATING ASSUMPTIONS & WORKING'!H33 -> 4725495.6 | I27: ='OPERATING ASSUMPTIONS & WORKING'!I33 -> 5231898.9 | J27: ='OPERATING ASSUMPTIONS & WORKING'!J33 -> 5705881.3
B28: Deferred revenue | C28: 1442969 | D28: 1520813 | E28: 1775730 | F28: ='OPERATING ASSUMPTIONS & WORKING'!F35 -> 2032217.6 | G28: ='OPERATING ASSUMPTIONS & WORKING'!G35 -> 2313906.8 | H28: ='OPERATING ASSUMPTIONS & WORKING'!H35 -> 2597639.9 | I28: ='OPERATING ASSUMPTIONS & WORKING'!I35 -> 2877419.9 | J28: ='OPERATING ASSUMPTIONS & WORKING'!J35 -> 3137332
B29: Short-term debt | C29: 399844 | D29: 1784453 | E29: 998865 | F29: =-SCHEDULES!G32 -> 1526000 | G29: =-SCHEDULES!H32 -> 3500000 | H29: =-SCHEDULES!I32 -> 4401000 | I29: =-SCHEDULES!J32 -> 2292000 | J29: =-SCHEDULES!K32 -> 0
B30: Total current liabilities | C30: =C24+C26+C27+C28+C29 -> 8860655 | D30: =D24+D26+D27+D28+D29 -> 10755400 | E30: =E24+E26+E27+E28+E29 -> 10980930 | F30: =F24+F26+F27+F28+F29 -> 13370107 | G30: =G24+G26+G27+G28+G29 -> 16861847 | H30: =H24+H26+H27+H28+H29 -> 19252884 | I30: =I24+I26+I27+I28+I29 -> 18597973 | J30: =J24+J26+J27+J28+J29 -> 17620875
B31: Non-current content liabilities | C31: 2578173 | D31: 1780806 | E31: 1579476 | F31: =F32*SCHEDULES!F22 -> 2386115.6 | G31: =G32*SCHEDULES!G22 -> 2671484.6 | H31: =H32*SCHEDULES!H22 -> 2956974.2 | I31: =I32*SCHEDULES!I22 -> 3224007.9 | J31: =J32*SCHEDULES!J22 -> 3461722.3
B32: % of Content Spend | C32: =C31/SCHEDULES!C22 -> 0.20535516 | D32: =D31/SCHEDULES!D22 -> 0.10976627 | E32: =E31/SCHEDULES!E22 -> 0.092385295 | F32: =AVERAGE($C$32:$E$32) -> 0.13583558 | G32: =AVERAGE($C$32:$E$32) -> 0.13583558 | H32: =AVERAGE($C$32:$E$32) -> 0.13583558 | I32: =AVERAGE($C$32:$E$32) -> 0.13583558 | J32: =AVERAGE($C$32:$E$32) -> 0.13583558
B33: Long-term debt | C33: 14143417 | D33: 13798351 | E33: 13463971 | F33: =SCHEDULES!F34-'FORECASTED BALANCE SHEET'!F29 -> 11936836 | G33: =SCHEDULES!G34-'FORECASTED BALANCE SHEET'!G29 -> 8436836 | H33: =SCHEDULES!H34-'FORECASTED BALANCE SHEET'!H29 -> 4035836 | I33: =SCHEDULES!I34-'FORECASTED BALANCE SHEET'!I29 -> 1743836 | J33: =SCHEDULES!J34-'FORECASTED BALANCE SHEET'!J29 -> 1743836
B34: Other non-current liabilities | C34: 2561434 | D34: 2552250 | E34: 2957128 | F34: =F35*'FORECASTED P&L '!F11 -> 3579193.6 | G34: =G35*'FORECASTED P&L '!G11 -> 4067348.8 | H34: =H35*'FORECASTED P&L '!H11 -> 4570555.8 | I34: =I35*'FORECASTED P&L '!I11 -> 5060355.1 | J34: =J35*'FORECASTED P&L '!J11 -> 5518796.5
B35: % of Revenues | C35: =C34/'FORECASTED P&L '!C11 -> 0.075954436 | D35: =D34/'FORECASTED P&L '!D11 -> 0.065440687 | E35: =E34/'FORECASTED P&L '!E11 -> 0.065447749 | F35: =AVERAGE($C$35:$E$35) -> 0.068947624 | G35: =AVERAGE($C$35:$E$35) -> 0.068947624 | H35: =AVERAGE($C$35:$E$35) -> 0.068947624 | I35: =AVERAGE($C$35:$E$35) -> 0.068947624 | J35: =AVERAGE($C$35:$E$35) -> 0.068947624
B36: Total liabilities | C36: =C30+C31+C33+C34 -> 28143679 | D36: =D30+D31+D33+D34 -> 28886807 | E36: =E30+E31+E33+E34 -> 28981505 | F36: =F30+F31+F33+F34 -> 31272252 | G36: =G30+G31+G33+G34 -> 32037516 | H36: =H30+H31+H33+H34 -> 30816250 | I36: =I30+I31+I33+I34 -> 28626172 | J36: =J30+J31+J33+J34 -> 28345230
B37: Stockholders’ equity:
B38: Common stock | C38: 5145172 | D38: 6252126 | E38: 7286410 | F38: =E38+'OPERATING ASSUMPTIONS & WORKING'!F39 -> 7722592.8 | G38: =F38+'OPERATING ASSUMPTIONS & WORKING'!G39 -> 8218265.3 | H38: =G38+'OPERATING ASSUMPTIONS & WORKING'!H39 -> 8775261.6 | I38: =H38+'OPERATING ASSUMPTIONS & WORKING'!I39 -> 9391948 | J38: =I38+'OPERATING ASSUMPTIONS & WORKING'!J39 -> 10064503
B39: Treasury stock | C39: -6922200 | D39: -13171638 | E39: -22372658 | F39: =-24644078.4+1160763.9 -> -23483314 | G39: =-25362081.7+1160764 -> -24201318 | H39: =-26145404+1160763.9 -> -24984640 | I39: =-27001314.4+1160764 -> -25840550 | J39: =-27943790.9+1160763.9 -> -26783027
B40: Accumulated other comprehensive income | C40: -223945 | D40: 362162 | E40: -580382 | F40: =$E$40 -> -580382 | G40: =$E$40 -> -580382 | H40: =$E$40 -> -580382 | I40: =$E$40 -> -580382 | J40: =$E$40 -> -580382
B41: Retained earnings | C41: 22589286 | D41: 31300917 | E41: 42282118 | F41: =E41+'FORECASTED P&L '!F27 -> 55631428 | G41: =F41+'FORECASTED P&L '!G27 -> 71840681 | H41: =G41+'FORECASTED P&L '!H27 -> 91246324 | I41: =H41+'FORECASTED P&L '!I27 -> 1.1401658e+08 | J41: =I41+'FORECASTED P&L '!J27 -> 1.4011388e+08
B42: Total stockholders’ equity | C42: =C38+C39+C40+C41 -> 20588313 | D42: =D38+D39+D40+D41 -> 24743567 | E42: =E38+E39+E40+E41 -> 26615488 | F42: =F38+F39+F40+F41 -> 39290324 | G42: =G38+G39+G40+G41 -> 55277246 | H42: =H38+H39+H40+H41 -> 74456563 | I42: =I38+I39+I40+I41 -> 96987594 | J42: =J38+J39+J40+J41 -> 1.2281497e+08
B43: Total liabilities and stockholders’ equity | C43: =C36+C42 -> 48731992 | D43: =D36+D42 -> 53630374 | E43: =E36+E42 -> 55596993 | F43: =F36+F42 -> 70562577 | G43: =G36+G42 -> 87314763 | H43: =H36+H42 -> 1.0527281e+08 | I43: =I36+I42 -> 1.2561377e+08 | J43: =J36+J42 -> 1.511602e+08
B45: Check | C45: =ROUND(C43-C20,0) -> 0 | D45: =ROUND(D43-D20,0) -> 0 | E45: =ROUND(E43-E20,0) -> 0 | F45: =ROUND(F43-F20,0) -> 0 | G45: =ROUND(G43-G20,0) -> 0 | H45: =ROUND(H43-H20,0) -> 0 | I45: =ROUND(I43-I20,0) -> 0 | J45: =ROUND(J43-J20,0) -> 0

Sheet FORECASTED CASH FLOW STATEMENT
B6: FORECASTED CASH FLOW STATEMENT
B8: ($ in thousands) | C8: 2024 | D8: =C8+1 -> 2025 | E8: 2026 | F8: =E8+1 -> 2027 | G8: =F8+1 -> 2028 | H8: =G8+1 -> 2029 | I8: =H8+1 -> 2030
B9: EBIT | C9: ='FORECASTED P&L '!D20 -> 10088700 | D9: ='FORECASTED P&L '!E20 -> 12993214 | E9: ='FORECASTED P&L '!F20 -> 15762890 | F9: ='FORECASTED P&L '!G20 -> 19035983 | G9: ='FORECASTED P&L '!H20 -> 22648425 | H9: ='FORECASTED P&L '!I20 -> 26461739 | I9: ='FORECASTED P&L '!J20 -> 30364621
B10: Operating Taxes | C10: =-(C9*C11) -> -1269509.1 | D10: =-(D9*D11) -> -1778396.8 | E10: =-(E9*E11) -> -2236300.1 | F10: =-(F9*F11) -> -2795837.7 | G10: =-(G9*G11) -> -3439643.6 | H10: =-(H9*H11) -> -4151084.8 | I10: =-(I9*I11) -> -4915157.7
B11: Tax Rate | C11: ='FORECASTED P&L '!D26 -> 0.12583475 | D11: ='FORECASTED P&L '!E26 -> 0.1368712 | E11: ='FORECASTED P&L '!F26 -> 0.1418712 | F11: ='FORECASTED P&L '!G26 -> 0.1468712 | G11: ='FORECASTED P&L '!H26 -> 0.1518712 | H11: ='FORECASTED P&L '!I26 -> 0.1568712 | I11: ='FORECASTED P&L '!J26 -> 0.1618712
B12: NOPAT | C12: =C9+C10 -> 8819190.9 | D12: =D9+D10 -> 11214817 | E12: =E9+E10 -> 13526589 | F12: =F9+F10 -> 16240145 | G12: =G9+G10 -> 19208782 | H12: =H9+H10 -> 22310654 | I12: =I9+I10 -> 25449463
B13: Amortization | C13: =SCHEDULES!D24 -> 15301517 | D13: =SCHEDULES!E24 -> 16422166 | E13: =SCHEDULES!F24 -> 16176651 | F13: =SCHEDULES!G24 -> 17298180 | G13: =SCHEDULES!H24 -> 18734665 | H13: =SCHEDULES!I24 -> 20341248 | I13: =SCHEDULES!J24 -> 21993919
B14: Depreciation | C14: =SCHEDULES!D14 -> 328914 | D14: =SCHEDULES!E14 -> 333389 | E14: =SCHEDULES!F14 -> 249144.31 | F14: =SCHEDULES!G14 -> 316123.65 | G14: =SCHEDULES!H14 -> 397187.23 | H14: =SCHEDULES!I14 -> 492061.23 | I14: =SCHEDULES!J14 -> 599899.98
B15: Gross Cash Flow | C15: =C12+C13+C14 -> 24449622 | D15: =D12+D13+D14 -> 27970372 | E15: =E12+E13+E14 -> 29952385 | F15: =F12+F13+F14 -> 33854449 | G15: =G12+G13+G14 -> 38340634 | H15: =H12+H13+H14 -> 43143964 | I15: =I12+I13+I14 -> 48043282
B16: Accounts Payable | C16: ='OPERATING ASSUMPTIONS & WORKING'!D31-'OPERATING ASSUMPTIONS & WORKING'!C31 -> 152497 | D16: ='OPERATING ASSUMPTIONS & WORKING'!E31-'OPERATING ASSUMPTIONS & WORKING'!D31 -> 703 | E16: ='OPERATING ASSUMPTIONS & WORKING'!F31-'OPERATING ASSUMPTIONS & WORKING'!E31 -> 142851.61 | F16: ='OPERATING ASSUMPTIONS & WORKING'!G31-'OPERATING ASSUMPTIONS & WORKING'!F31 -> 125248.34 | G16: ='OPERATING ASSUMPTIONS & WORKING'!H31-'OPERATING ASSUMPTIONS & WORKING'!G31 -> 79683.909 | H16: ='OPERATING ASSUMPTIONS & WORKING'!I31-'OPERATING ASSUMPTIONS & WORKING'!H31 -> 100749.99 | I16: ='OPERATING ASSUMPTIONS & WORKING'!J31-'OPERATING ASSUMPTIONS & WORKING'!I31 -> 76122.348
B17: Deferred Revenue | C17: ='OPERATING ASSUMPTIONS & WORKING'!D35-'OPERATING ASSUMPTIONS & WORKING'!C35 -> 77844 | D17: ='OPERATING ASSUMPTIONS & WORKING'!E35-'OPERATING ASSUMPTIONS & WORKING'!D35 -> 254917 | E17: ='OPERATING ASSUMPTIONS & WORKING'!F35-'OPERATING ASSUMPTIONS & WORKING'!E35 -> 256487.57 | F17: ='OPERATING ASSUMPTIONS & WORKING'!G35-'OPERATING ASSUMPTIONS & WORKING'!F35 -> 281689.25 | G17: ='OPERATING ASSUMPTIONS & WORKING'!H35-'OPERATING ASSUMPTIONS & WORKING'!G35 -> 283733.1 | H17: ='OPERATING ASSUMPTIONS & WORKING'!I35-'OPERATING ASSUMPTIONS & WORKING'!H35 -> 279779.95 | I17: ='OPERATING ASSUMPTIONS & WORKING'!J35-'OPERATING ASSUMPTIONS & WORKING'!I35 -> 259912.16
B18: Accrued Expenses & Other Liabilities | C18: ='OPERATING ASSUMPTIONS & WORKING'!D33-'OPERATING ASSUMPTIONS & WORKING'!C33 -> 352584 | D18: ='OPERATING ASSUMPTIONS & WORKING'!E33-'OPERATING ASSUMPTIONS & WORKING'!D33 -> 1064325 | E18: ='OPERATING ASSUMPTIONS & WORKING'!F33-'OPERATING ASSUMPTIONS & WORKING'!E33 -> 479657.66 | F18: ='OPERATING ASSUMPTIONS & WORKING'!G33-'OPERATING ASSUMPTIONS & WORKING'!F33 -> 504703.5 | G18: ='OPERATING ASSUMPTIONS & WORKING'!H33-'OPERATING ASSUMPTIONS & WORKING'!G33 -> 520265.43 | H18: ='OPERATING ASSUMPTIONS & WORKING'!I33-'OPERATING ASSUMPTIONS & WORKING'!H33 -> 506403.32 | I18: ='OPERATING ASSUMPTIONS & WORKING'!J33-'OPERATING ASSUMPTIONS & WORKING'!I33 -> 473982.35
B19: Other Current Assets | C19: =-('OPERATING ASSUMPTIONS & WORKING'!D27-'OPERATING ASSUMPTIONS & WORKING'!C27) -> -736393 | D19: =-('OPERATING ASSUMPTIONS & WORKING'!E27-'OPERATING ASSUMPTIONS & WORKING'!D27) -> -441192 | E19: =-('OPERATING ASSUMPTIONS & WORKING'!F27-'OPERATING ASSUMPTIONS & WORKING'!E27) -> -548274.27 | F19: =-('OPERATING ASSUMPTIONS & WORKING'!G27-'OPERATING ASSUMPTIONS & WORKING'!F27) -> -696321.61 | G19: =-('OPERATING ASSUMPTIONS & WORKING'!H27-'OPERATING ASSUMPTIONS & WORKING'!G27) -> -599905.32 | H19: =-('OPERATING ASSUMPTIONS & WORKING'!I27-'OPERATING ASSUMPTIONS & WORKING'!H27) -> -620178.84 | I19: =-('OPERATING ASSUMPTIONS & WORKING'!J27-'OPERATING ASSUMPTIONS & WORKING'!I27) -> -600627.14
B20: Investments in Working Capital | C20: =C16+C17+C18+C19 -> -153468 | D20: =D16+D17+D18+D19 -> 878753 | E20: =E16+E17+E18+E19 -> 330722.57 | F20: =F16+F17+F18+F19 -> 215319.47 | G20: =G16+G17+G18+G19 -> 283777.13 | H20: =H16+H17+H18+H19 -> 266754.42 | I20: =I16+I17+I18+I19 -> 209389.72
B21: Content Assets | C21: =SCHEDULES!D22 -> 16223617 | D21: =SCHEDULES!E22 -> 17096617 | E21: =SCHEDULES!F22 -> 17566205 | F21: =SCHEDULES!G22 -> 19667047 | G21: =SCHEDULES!H22 -> 21768776 | H21: =SCHEDULES!I22 -> 23734636 | I21: =SCHEDULES!J22 -> 25484652
B22: PP&E | C22: =SCHEDULES!D12 -> 439538 | D22: =SCHEDULES!E12 -> 688220 | E22: =SCHEDULES!F12 -> 920490.41 | F22: =SCHEDULES!G12 -> 1193512.9 | G22: =SCHEDULES!H12 -> 1506898.4 | H22: =SCHEDULES!I12 -> 1851869.2 | I22: =SCHEDULES!J12 -> 2219747.1
B23: Capex | C23: =-(C21+C22) -> -16663155 | D23: =-(D21+D22) -> -17784837 | E23: =-(E21+E22) -> -18486696 | F23: =-(F21+F22) -> -20860560 | G23: =-(G21+G22) -> -23275675 | H23: =-(H21+H22) -> -25586505 | I23: =-(I21+I22) -> -27704399
B24: UFCF | C24: =C15+C20+C23 -> 7632998.9 | D24: =D15+D20+D23 -> 11064288 | E24: =E15+E20+E23 -> 11796412 | F24: =F15+F20+F23 -> 13209208 | G24: =G15+G20+G23 -> 15348737 | H24: =H15+H20+H23 -> 17824213 | I24: =I15+I20+I23 -> 20548273
B25: Debt Taken/(Repaid) | C25: =SCHEDULES!D32 -> -400000 | D25: =SCHEDULES!E32 -> -1833450 | E25: =SCHEDULES!F32 -> -1000000 | F25: =SCHEDULES!G32 -> -1526000 | G25: =SCHEDULES!H32 -> -3500000 | H25: =SCHEDULES!I32 -> -4401000 | I25: =SCHEDULES!J32 -> -2292000
B26: Interest Expense | C26: =SCHEDULES!D36 -> -718733 | D26: =SCHEDULES!E36 -> -776510 | E26: =SCHEDULES!F36 -> -615117.29 | F26: =SCHEDULES!G36 -> -533457.48 | G26: =SCHEDULES!H36 -> -368605.56 | H26: =SCHEDULES!I36 -> -172289.93 | I26: =SCHEDULES!J36 -> -72700.563
B27: Diff b/w Operating & Actual Taxes | C27: ='FORECASTED P&L '!D25-'FORECASTED CASH FLOW STATEMENT'!C10 -> 15483.086 | D27: ='FORECASTED P&L '!E25-'FORECASTED CASH FLOW STATEMENT'!D10 -> 37045.834 | E27: ='FORECASTED P&L '!F25-'FORECASTED CASH FLOW STATEMENT'!E10 -> 29308.93 | F27: ='FORECASTED P&L '!G25-'FORECASTED CASH FLOW STATEMENT'!F10 -> 5318.3765 | G27: ='FORECASTED P&L '!H25-'FORECASTED CASH FLOW STATEMENT'!G10 -> -35251.218 | H27: ='FORECASTED P&L '!I25-'FORECASTED CASH FLOW STATEMENT'!H10 -> -85512.598 | I27: ='FORECASTED P&L '!J25-'FORECASTED CASH FLOW STATEMENT'!I10 -> -125119.37
B28: Net Cash Flow | C28: =C24+C25+C26+C27 -> 6529749 | D28: =D24+D25+D26+D27 -> 8491374 | E28: =E24+E25+E26+E27 -> 10210603 | F28: =F24+F25+F26+F27 -> 11155069 | G28: =G24+G25+G26+G27 -> 11444880 | H28: =H24+H25+H26+H27 -> 13165410 | I28: =I24+I25+I26+I27 -> 18058453

Sheet WACC
B6: WACC CALCULATION
B8: Cost of Equity
B9: Risk Free Rate | C9: 0.0436
B10: Equity Risk Premium | C10: 0.0446
B11: Beta | C11: 1.1
B12: Cost of Equity | C12: =C9+C11*C10 -> 0.09266
B14: Cost of Debt
B15: Pre-Tax Cost of Debt | C15: =C9+0.9% -> 0.0526
B16: Tax Rate | C16: ='FORECASTED P&L '!F26 -> 0.1418712
B17: Cost of Debt | C17: =C15*(1-C16) -> 0.045137575
B19: WACC
B20: Market Value of Equity ($K) | C20: 391442000
B21: Total Debt ($K) | C21: ='FORECASTED BALANCE SHEET'!F29+'FORECASTED BALANCE SHEET'!F33 -> 13462836
B22: Total Capital ($K) | C22: =C20+C21 -> 404904836
B23: Equity Weight | C23: =C20/C22 -> 0.96675062
B24: Debt Weight | C24: =C21/C22 -> 0.033249383
B25: WACC | C25: =C12*C23+C17*C24 -> 0.091079909
B26: Termina Growth Rate (g) | C26: 0.035
B28: Sensitivity Analysis - Intrinsic Value per Share vs WACC \ g
B29: =DCF!C22 -> 73.609364 | C29: 0.025 | D29: 0.03 | E29: 0.035 | F29: 0.04 | G29: 0.045
B30: 0.0811 | C30: 76.142688 | D30: 82.359757 | E30: 89.92543 | F30: 99.3319 | G30: 111.34404
B31: 0.0861 | C31: 69.743635 | D31: 74.848092 | E31: 80.951465 | F31: 88.378779 | G31: 97.613226
B32: 0.0911 | C32: 64.317501 | D32: 68.57086 | E32: 73.582393 | F32: 79.574656 | G32: 86.86676
B33: 0.0961 | C33: 59.658922 | D33: 63.24782 | E33: 67.424099 | F33: 72.344812 | G33: 78.228484
B34: 0.1011 | C34: 55.616506 | D34: 58.677564 | E34: 62.201717 | F34: 66.302655 | G34: 71.134597

Sheet DCF
B6: DCF VALUATION
B8: ($ in thousands) | C8: 2026 | D8: =C8+1 -> 2027 | E8: =D8+1 -> 2028 | F8: =E8+1 -> 2029 | G8: =F8+1 -> 2030
B9: UFCF | C9: ='FORECASTED CASH FLOW STATEMENT'!E24 -> 11796412 | D9: ='FORECASTED CASH FLOW STATEMENT'!F24 -> 13209208 | E9: ='FORECASTED CASH FLOW STATEMENT'!G24 -> 15348737 | F9: ='FORECASTED CASH FLOW STATEMENT'!H24 -> 17824213 | G9: ='FORECASTED CASH FLOW STATEMENT'!I24 -> 20548273
B10: Projection Period (Years) | C10: 1 | D10: 2 | E10: 3 | F10: 4 | G10: 5
B11: Discount Factor | C11: =1/(1+WACC!$C$25)^DCF!C10 -> 0.91652315 | D11: =1/(1+WACC!$C$25)^DCF!D10 -> 0.84001469 | E11: =1/(1+WACC!$C$25)^DCF!E10 -> 0.76989292 | F11: =1/(1+WACC!$C$25)^DCF!F10 -> 0.70562468 | G11: =1/(1+WACC!$C$25)^DCF!G10 -> 0.64672136
B12: PV of UFCF | C12: =C9*C11 -> 10811684 | D12: =D9*D11 -> 11095929 | E12: =E9*E11 -> 11816884 | F12: =F9*F11 -> 12577205 | G12: =G9*G11 -> 13289007
B14: Terminal Value | C14: ='FORECASTED CASH FLOW STATEMENT'!I24*(1+WACC!C26)/(WACC!C25-WACC!C26) -> 3.7923497e+08
B15: PV of Terminal Value | C15: =C14*G11 -> 2.4525936e+08
B16: Sum of PV of UFCF | C16: =SUM(C12:G12) -> 59590709
B17: Enterprise Value | C17: =C16+C15 -> 3.0485007e+08
B18: Cash & Cash Equivalents | C18: ='FORECASTED BALANCE SHEET'!F11 -> 19244284
B19: Total Debt | C19: =WACC!C21 -> 13462836
B20: Equity Value | C20: =C17+C18-C19 -> 3.1063152e+08
B21: Shares Outstanding | C21: 4220000
B22: Intrinsic Value per Share | C22: =C20/C21 -> 73.609364

Sheet Sheet3
